climatextract/__init__.py
climatextract/azure_credential.json
climatextract/config.py
climatextract/data_lake_manager.py
climatextract/edit_unit_normalization.py
climatextract/evaluate_helpers.py
climatextract/evaluator.py
climatextract/experiment_setup.py
climatextract/helpers.py
climatextract/main.py
climatextract/page_text_and_table_extractor.py
climatextract/params.py
climatextract/pipeline.py
climatextract/preprocessing.py
climatextract/prompts_with_prompt_parsers.py
climatextract/resolve_duplicates.py
climatextract/semantic_search.py
climatextract/table_helper.py
climatextract-0.2.1.dist-info/METADATA
climatextract-0.2.1.dist-info/WHEEL
climatextract-0.2.1.dist-info/top_level.txt
climatextract-0.2.1.dist-info/RECORD
