Metadata-Version: 2.4
Name: climatextract
Version: 0.2.1
Summary: Extract CO2 emissions data from PDF sustainability reports using LLMs
Author: ClimXtract Team
License: MIT
Keywords: co2,emissions,sustainability,pdf,extraction,llm,nlp
Classifier: Development Status :: 3 - Alpha
Classifier: Intended Audience :: Science/Research
Classifier: License :: OSI Approved :: MIT License
Classifier: Programming Language :: Python :: 3
Classifier: Programming Language :: Python :: 3.11
Classifier: Programming Language :: Python :: 3.12
Classifier: Topic :: Scientific/Engineering :: Information Analysis
Requires-Python: >=3.11
Requires-Dist: azure-storage-blob
Requires-Dist: docling>=2.28.4
Requires-Dist: duckdb>=1.2.2
Requires-Dist: llama-index>=0.12.29
Requires-Dist: llama-index-embeddings-azure-openai>=0.3.2
Requires-Dist: mlflow>=2.21.3
Requires-Dist: pdf2image>=1.17.0
Requires-Dist: PyPDF2>=3.0.1
Requires-Dist: tiktoken>=0.11.0
Requires-Dist: timm>=1.0.15
Requires-Dist: pandas
Requires-Dist: numpy
Provides-Extra: dev
Requires-Dist: pytest>=8.3.5; extra == "dev"
